README.md
setup.py
Kiosk_Client.egg-info/PKG-INFO
Kiosk_Client.egg-info/SOURCES.txt
Kiosk_Client.egg-info/dependency_links.txt
Kiosk_Client.egg-info/requires.txt
Kiosk_Client.egg-info/top_level.txt
kiosk_client/__init__.py
kiosk_client/__main__.py
kiosk_client/__version__.py
kiosk_client/cost.py
kiosk_client/cost_test.py
kiosk_client/job.py
kiosk_client/job_test.py
kiosk_client/manager.py
kiosk_client/manager_test.py
kiosk_client/settings.py
kiosk_client/utils.py
kiosk_client/utils_test.py