Metadata-Version: 2.1
Name: Kiosk-Client
Version: 0.8.4
Summary: CLI client for the DeepCell Kiosk.
Home-page: https://github.com/vanvalenlab/kiosk-client
Author: Van Valen Lab
Author-email: vanvalenlab@gmail.com
License: LICENSE
Download-URL: https://github.com/vanvalenlab/kiosk-client/tarball/0.8.4
Platform: UNKNOWN
Classifier: Programming Language :: Python
Classifier: Programming Language :: Python :: 2
Classifier: Programming Language :: Python :: 2.7
Classifier: Programming Language :: Python :: 3
Classifier: Programming Language :: Python :: 3.5
Classifier: Programming Language :: Python :: 3.6
Classifier: Programming Language :: Python :: 3.7
Classifier: Programming Language :: Python :: 3.8
Requires-Python: >=2.7, !=3.0.*, !=3.1.*, !=3.2.*, !=3.3.*, !=3.4.*
Provides-Extra: tests
